LICENSE
README.md
__init__.py
aligngraph.py
choosepaths.py
diversity.py
edit_distance.py
error_profile.py
iterconsensus.py
manipulate_single_genome.py
polisher.py
pvga.py
pyproject.toml
readgraph.py
utils.py
writesequence.py
pvga/__init__.py
pvga/aligngraph.py
pvga/choosepaths.py
pvga/diversity.py
pvga/edit_distance.py
pvga/error_profile.py
pvga/iterconsensus.py
pvga/manipulate_single_genome.py
pvga/polisher.py
pvga/pvga.py
pvga/readgraph.py
pvga/utils.py
pvga/writesequence.py
pvga.egg-info/PKG-INFO
pvga.egg-info/SOURCES.txt
pvga.egg-info/dependency_links.txt
pvga.egg-info/requires.txt
pvga.egg-info/top_level.txt
pvga-0.1.2.dist-info/LICENSE
pvga-0.1.2.dist-info/METADATA
pvga-0.1.2.dist-info/WHEEL
pvga-0.1.2.dist-info/entry_points.txt
pvga-0.1.2.dist-info/top_level.txt
pvga-0.1.2.dist-info/RECORD
